pyvalidify/__init__.py
pyvalidify/decorators.py
pyvalidify/descriptor.py
pyvalidify/type_hints.py
pyvalidify/validator.py
pyvalidify-1.0.1.dist-info/LICENSE
pyvalidify-1.0.1.dist-info/METADATA
pyvalidify-1.0.1.dist-info/WHEEL
pyvalidify-1.0.1.dist-info/RECORD
