Metadata-Version: 2.1
Name: pyvalidify
Version: 1.0.1
Summary: Python library for automated and manual runtime data type validation.
License: MIT
Author: Patryk Jesionka
Author-email: jesionka.patryk13@gmail.com
Requires-Python: >=3.10,<4.0
Classifier: License :: OSI Approved :: MIT License
Classifier: Programming Language :: Python :: 3
Classifier: Programming Language :: Python :: 3.10
Classifier: Programming Language :: Python :: 3.11
Classifier: Programming Language :: Python :: 3.12
